{
  "uuSubAppDataStore": {
    "primary": {
      "type": "uuAppObjectStore",
      "realization": "MongoDB",
      "schemaMap": {
        "newsMain": {
          "realization": "dao/NewsMainMongo"
        },
        "article": {
          "realization": "dao/NewsArticleMongo", 
          "maxNoi": 1000000
        },
        "newspaper": {
          "realization": "dao/NewsNewspaperMongo",
          "maxNoi": 1000
        },
        "topic": {
          "realization": "dao/NewsTopicMongo",
          "maxNoi": 1000
        }
      }
    }
  }
}
